Metadata-Version: 1.1
Name: iseeu
Version: 0.1.2
Summary: ISeeU: Visually interpretable deep learning for mortality prediction inside the ICU
Home-page: https://github.com/williamcaicedo/ISeeU
Author: William Caicedo-Torres
Author-email: UNKNOWN
License: MIT
Keywords: Deep Learning,Mortality prediction,Shapley values
Platform: UNKNOWN
Classifier: Development Status :: 3 - Alpha
Classifier: License :: OSI Approved :: MIT License
